admin_export/__init__.py
admin_export/deco.py
admin_export/exporter.py
admin_export/urls.py
admin_export/templates/admin_export/admin/change_list.html
admin_export/templatetags/__init__.py
admin_export/templatetags/export_tags.py
django_simple_export-0.1.dist-info/DESCRIPTION.rst
django_simple_export-0.1.dist-info/METADATA
django_simple_export-0.1.dist-info/RECORD
django_simple_export-0.1.dist-info/WHEEL
django_simple_export-0.1.dist-info/metadata.json
django_simple_export-0.1.dist-info/top_level.txt
