Metadata-Version: 2.0
Name: django-simple-export
Version: 0.1
Summary: A simple Django app to export admin models as excel files.
Home-page: https://github.com/lkiarest/django-simple-export
Author: lkiarest
Author-email: rushi_wowen@163.com
License: MIT License
Platform: UNKNOWN
Classifier: Environment :: Web Environment
Classifier: Framework :: Django
Classifier: Framework :: Django :: 2.0
Classifier: Intended Audience :: Developers
Classifier: License :: OSI Approved :: MIT License
Classifier: Operating System :: OS Independent
Classifier: Programming Language :: Python
Classifier: Programming Language :: Python :: 3.5
Classifier: Programming Language :: Python :: 3.6
Classifier: Topic :: Internet :: WWW/HTTP
Classifier: Topic :: Internet :: WWW/HTTP :: Dynamic Content
Requires-Dist: django
Requires-Dist: xlwt
